[
  "[{\"IdLists\":\"Pro-D-1,Pro-D-4,NE-D-1,MB-D-1,MB-D-4,MCE-D-15,MCE-D-4,MCE-D-1\",\"TotalCount\":\"8\",\"color\":\"#77933c\",\"DA_Rel_Test\":8,\"Effort\":0,\"count\":\"1\"},{\"IdLists\":\"Pro-D-9,NE-D-9,MB-D-9,MCE-D-10,NE-D-10,Pro-D-10,MCE-D-9,MB-D-10\",\"TotalCount\":\"8\",\"color\":\"#77933c\",\"DA_Rel_Test\":8,\"Effort\":0,\"count\":\"2\"},{\"IdLists\":\"NE-D-11\",\"TotalCount\":\"1\",\"color\":\"#77933c\",\"DA_Rel_Test\":1,\"Effort\":0,\"count\":\"3\"},{\"IdLists\":\"MB-D-13\",\"TotalCount\":\"1\",\"color\":\"#77933c\",\"DA_Rel_Test\":1,\"Effort\":0,\"count\":\"4\"},{\"IdLists\":\"Pro-D-7,NE-D-7,MB-D-7,MCE-D-21,NE-D-15,MCE-D-7\",\"TotalCount\":\"6\",\"color\":\"#77933c\",\"DA_Rel_Test\":6,\"Effort\":0,\"count\":\"5\"},{\"IdLists\":\"Pro-D-15\",\"TotalCount\":\"1\",\"color\":\"#77933c\",\"DA_Rel_Test\":1,\"Effort\":0,\"count\":\"6\"},{\"IdLists\":\"MCE-D-2\",\"TotalCount\":\"1\",\"color\":\"#ffc000\",\"DA_Rel_Test\":1,\"Effort\":0.16666666666666666,\"count\":\"7\"},{\"IdLists\":\"MCE-D-18\",\"TotalCount\":\"1\",\"color\":\"#ffc000\",\"DA_Rel_Test\":1,\"Effort\":0.5,\"count\":\"9\"},{\"IdLists\":\"Pro-D-3,NE-D-2,MB-D-2,MB-D-3,NE-D-3,MCE-D-17\",\"TotalCount\":\"6\",\"color\":\"#fe0000\",\"DA_Rel_Test\":6,\"Effort\":3.9999999999999996,\"count\":\"10\"},{\"IdLists\":\"Pro-D-2,MCE-D-3\",\"TotalCount\":\"2\",\"color\":\"#fe0000\",\"DA_Rel_Test\":2,\"Effort\":2,\"count\":\"12\"},{\"IdLists\":\"Pro-D-5,MCE-D-16,Pro-D-13\",\"TotalCount\":\"3\",\"color\":\"#fe0000\",\"DA_Rel_Test\":3,\"Effort\":4,\"count\":\"14\"},{\"IdLists\":\"NE-D-8,NE-D-5,MCE-D-6\",\"TotalCount\":\"3\",\"color\":\"#fe0000\",\"DA_Rel_Test\":3,\"Effort\":4.5,\"count\":\"15\"},{\"IdLists\":\"MB-D-5,NE-D-4,MCE-D-12,NE-D-12\",\"TotalCount\":\"4\",\"color\":\"#fe0000\",\"DA_Rel_Test\":4,\"Effort\":6.666666666666667,\"count\":\"16\"},{\"IdLists\":\"MB-D-6,MCE-D-14\",\"TotalCount\":\"2\",\"color\":\"#fe0000\",\"DA_Rel_Test\":2,\"Effort\":3.6666666666666665,\"count\":\"17\"},{\"IdLists\":\"Pro-D-6,Pro-D-8,MB-D-8,NE-D-6,MCE-D-19,MCE-D-20,MCE-D-22,NE-D-16,NE-D-14,Pro-D-14,Pro-D-16,MCE-D-8,MCE-D-5\",\"TotalCount\":\"13\",\"color\":\"#fe0000\",\"DA_Rel_Test\":13,\"Effort\":26,\"count\":\"18\"},{\"IdLists\":\"MCE-D-11,MCE-D-13,NE-D-13,Pro-D-11,Pro-D-12,MB-D-11,MB-D-12\",\"TotalCount\":\"7\",\"color\":\"#fe0000\",\"DA_Rel_Test\":7,\"Effort\":16.333333333333336,\"count\":\"20\"}]",
  "[]",
  "DA_Rel_Test",
  "67.83333333333333"
]